llama_index/storage/docstore/azure/__init__.py
llama_index/storage/docstore/azure/base.py
llama_index_storage_docstore_azure-0.4.1.dist-info/METADATA
llama_index_storage_docstore_azure-0.4.1.dist-info/WHEEL
llama_index_storage_docstore_azure-0.4.1.dist-info/licenses/LICENSE
llama_index_storage_docstore_azure-0.4.1.dist-info/RECORD
